tests/__init__.py
tests/test_minimise.py
tests/test_spec.py
tests/test_util.py
tests/test_vars.py
tests/util.py
varz/__init__.py
varz/_version.py
varz/adam.py
varz/minimise.py
varz/spec.py
varz/util.py
varz/vars.py
varz/autograd/__init__.py
varz/autograd/minimise.py
varz/jax/__init__.py
varz/jax/minimise.py
varz/tensorflow/__init__.py
varz/tensorflow/minimise.py
varz/torch/__init__.py
varz/torch/minimise.py
varz-0.8.1.dist-info/LICENCE.txt
varz-0.8.1.dist-info/METADATA
varz-0.8.1.dist-info/WHEEL
varz-0.8.1.dist-info/top_level.txt
varz-0.8.1.dist-info/RECORD
