Metadata-Version: 2.1
Name: varz
Version: 0.8.1
Summary: Painless variables in PyTorch and TensorFlow
Home-page: https://github.com/wesselb/varz
Author: Wessel Bruinsma
Author-email: wessel.p.bruinsma@gmail.com
License: MIT
Requires-Python: >=3.6
License-File: LICENCE.txt
Requires-Dist: numpy (>=1.16)
Requires-Dist: scipy (>=1.3)
Requires-Dist: plum-dispatch (>=2)
Requires-Dist: backends (>=1.4.3)
Requires-Dist: wbml (>=0.3)
